rdio_gmusic.py
setup.py
rdio_gmusic.egg-info/PKG-INFO
rdio_gmusic.egg-info/SOURCES.txt
rdio_gmusic.egg-info/dependency_links.txt
rdio_gmusic.egg-info/entry_points.txt
rdio_gmusic.egg-info/requires.txt
rdio_gmusic.egg-info/top_level.txt