Metadata-Version: 1.0
Name: rdio-gmusic
Version: 0.1
Summary: Rdio to Google Music Exporter
Home-page: https://github.com/rraval/rdio-gmusic
Author: Ronuk Raval
Author-email: ronuk.raval@gmail.com
License: MIT
Keywords: rdio google-music
Platform: UNKNOWN
